polarsgeoutilsbp-0.34.25.dist-info/METADATA
polarsgeoutilsbp-0.34.25.dist-info/WHEEL
polarsgeoutils/__init__.py
polarsgeoutils/polarsgeoutils.cpython-311-x86_64-linux-gnu.so
polarsgeoutilsbp-0.34.25.dist-info/RECORD
