Metadata-Version: 2.3
Name: polarsgeoutilsbp
Version: 0.34.25
